{
  "123456789": [
    {
      "orderReference": "ESIM-2024-12-001",
      "number": "ESIM-2024-12-001",
      "source": "telegram_mini_app",
      "customer": "123456789",
      "telegram_user_id": "123456789",
      "provider_product_id": "esim_1GB_7D_US_V2",
      "provider_base_price_usd": 10.99,
      "payment_method": "telegram_stars",
      "paymentType": "telegram_stars",
      "date": "2024-12-29",
      "time": "10:30:00",
      "status": "completed",
      "iccid": "8944123456789012345",
      "matchingId": "A1B2-C3D4-E5F6-G7H8",
      "smdpAddress": "http://rsp.truphone.com",
      "rspUrl": "http://rsp.truphone.com",
      "country_code": "US",
      "country_name": "United States",
      "plan_id": "esim_1GB_7D_US_V2",
      "plan_type": "standard",
      "plan_name": "1GB 7 Days",
      "bundle_name": "esim_1GB_7D_US_V2",
      "price": "12.99",
      "currency": "USD",
      "telegram_username": "test_user",
      "createdAt": "2024-12-29T10:30:00.000Z",
      "updatedAt": "2024-12-29T10:30:00.000Z",
      "qrCode": "https://api.qrserver.com/v1/create-qr-code/?size=300x300&data=LPA:1$rsp.truphone.com$A1B2-C3D4-E5F6-G7H8",
      "qr_code": "https://api.qrserver.com/v1/create-qr-code/?size=300x300&data=LPA:1$rsp.truphone.com$A1B2-C3D4-E5F6-G7H8"
    },
    {
      "orderReference": "ESIM-2024-12-002",
      "number": "ESIM-2024-12-002",
      "source": "telegram_mini_app",
      "customer": "123456789",
      "telegram_user_id": "123456789",
      "provider_product_id": "esim_3GB_30D_GB_V2",
      "provider_base_price_usd": 20.99,
      "payment_method": "telegram_stars",
      "paymentType": "telegram_stars",
      "date": "2024-12-28",
      "time": "14:15:00",
      "status": "completed",
      "iccid": "8944987654321098765",
      "matchingId": "X9Y8-Z7W6-V5U4-T3S2",
      "smdpAddress": "http://rsp.airalo.com",
      "rspUrl": "http://rsp.airalo.com",
      "country_code": "GB",
      "country_name": "United Kingdom",
      "plan_id": "esim_3GB_30D_GB_V2",
      "plan_type": "standard",
      "plan_name": "3GB 30 Days",
      "bundle_name": "esim_3GB_30D_GB_V2",
      "price": "24.99",
      "currency": "USD",
      "telegram_username": "test_user",
      "createdAt": "2024-12-28T14:15:00.000Z",
      "updatedAt": "2024-12-28T14:15:00.000Z",
      "qrCode": "https://api.qrserver.com/v1/create-qr-code/?size=300x300&data=LPA:1$rsp.airalo.com$X9Y8-Z7W6-V5U4-T3S2",
      "qr_code": "https://api.qrserver.com/v1/create-qr-code/?size=300x300&data=LPA:1$rsp.airalo.com$X9Y8-Z7W6-V5U4-T3S2"
    },
    {
      "orderReference": "ESIM-2024-12-003",
      "number": "ESIM-2024-12-003",
      "source": "telegram_mini_app",
      "customer": "123456789",
      "telegram_user_id": "123456789",
      "provider_product_id": "esim_unlimited_DE_V2",
      "provider_base_price_usd": 35.99,
      "payment_method": "bank_card",
      "paymentType": "bank_card",
      "date": "2024-12-27",
      "time": "09:00:00",
      "status": "completed",
      "iccid": "8944111122223333444",
      "matchingId": "M1N2-O3P4-Q5R6-S7T8",
      "smdpAddress": "http://rsp.holafly.com",
      "rspUrl": "http://rsp.holafly.com",
      "country_code": "DE",
      "country_name": "Germany",
      "plan_id": "esim_unlimited_DE_V2",
      "plan_type": "unlimited",
      "plan_name": "Unlimited 30 Days",
      "bundle_name": "esim_unlimited_DE_V2",
      "price": "39.99",
      "currency": "USD",
      "telegram_username": "test_user",
      "createdAt": "2024-12-27T09:00:00.000Z",
      "updatedAt": "2024-12-27T09:00:00.000Z",
      "qrCode": "https://api.qrserver.com/v1/create-qr-code/?size=300x300&data=LPA:1$rsp.holafly.com$M1N2-O3P4-Q5R6-S7T8",
      "qr_code": "https://api.qrserver.com/v1/create-qr-code/?size=300x300&data=LPA:1$rsp.holafly.com$M1N2-O3P4-Q5R6-S7T8"
    },
    {
      "orderReference": "ESIM-2024-12-004",
      "number": "ESIM-2024-12-004",
      "source": "telegram_mini_app",
      "customer": "123456789",
      "telegram_user_id": "123456789",
      "provider_product_id": "esim_5GB_14D_FR_V2",
      "provider_base_price_usd": 15.99,
      "payment_method": "telegram_stars",
      "paymentType": "telegram_stars",
      "date": "2024-12-26",
      "time": "16:45:00",
      "status": "completed",
      "iccid": "8944555566667777888",
      "matchingId": "K1L2-M3N4-O5P6-Q7R8",
      "smdpAddress": "http://rsp.nomad.com",
      "rspUrl": "http://rsp.nomad.com",
      "country_code": "FR",
      "country_name": "France",
      "plan_id": "esim_5GB_14D_FR_V2",
      "plan_type": "standard",
      "plan_name": "5GB 14 Days",
      "bundle_name": "esim_5GB_14D_FR_V2",
      "price": "18.99",
      "currency": "USD",
      "telegram_username": "test_user",
      "createdAt": "2024-12-26T16:45:00.000Z",
      "updatedAt": "2024-12-26T16:45:00.000Z",
      "qrCode": "https://api.qrserver.com/v1/create-qr-code/?size=300x300&data=LPA:1$rsp.nomad.com$K1L2-M3N4-O5P6-Q7R8",
      "qr_code": "https://api.qrserver.com/v1/create-qr-code/?size=300x300&data=LPA:1$rsp.nomad.com$K1L2-M3N4-O5P6-Q7R8"
    }
  ],
  "987654321": [
    {
      "orderReference": "ESIM-2024-12-005",
      "number": "ESIM-2024-12-005",
      "source": "telegram_mini_app",
      "customer": "987654321",
      "telegram_user_id": "987654321",
      "provider_product_id": "esim_2GB_15D_ES_V2",
      "provider_base_price_usd": 14.99,
      "payment_method": "telegram_stars",
      "paymentType": "telegram_stars",
      "date": "2024-12-25",
      "time": "11:20:00",
      "status": "completed",
      "iccid": "8944222233334444555",
      "matchingId": "P1Q2-R3S4-T5U6-V7W8",
      "smdpAddress": "http://rsp.truphone.com",
      "rspUrl": "http://rsp.truphone.com",
      "country_code": "ES",
      "country_name": "Spain",
      "plan_id": "esim_2GB_15D_ES_V2",
      "plan_type": "standard",
      "plan_name": "2GB 15 Days",
      "bundle_name": "esim_2GB_15D_ES_V2",
      "price": "16.99",
      "currency": "USD",
      "telegram_username": "maria_travel",
      "createdAt": "2024-12-25T11:20:00.000Z",
      "updatedAt": "2024-12-25T11:20:00.000Z",
      "qrCode": "https://api.qrserver.com/v1/create-qr-code/?size=300x300&data=LPA:1$rsp.truphone.com$P1Q2-R3S4-T5U6-V7W8",
      "qr_code": "https://api.qrserver.com/v1/create-qr-code/?size=300x300&data=LPA:1$rsp.truphone.com$P1Q2-R3S4-T5U6-V7W8"
    },
    {
      "orderReference": "ESIM-2024-12-006",
      "number": "ESIM-2024-12-006",
      "source": "telegram_mini_app",
      "customer": "987654321",
      "telegram_user_id": "987654321",
      "provider_product_id": "esim_10GB_30D_IT_V2",
      "provider_base_price_usd": 29.99,
      "payment_method": "bank_card",
      "paymentType": "bank_card",
      "date": "2024-12-24",
      "time": "13:45:00",
      "status": "completed",
      "iccid": "8944666677778888999",
      "matchingId": "Y1Z2-A3B4-C5D6-E7F8",
      "smdpAddress": "http://rsp.airalo.com",
      "rspUrl": "http://rsp.airalo.com",
      "country_code": "IT",
      "country_name": "Italy",
      "plan_id": "esim_10GB_30D_IT_V2",
      "plan_type": "standard",
      "plan_name": "10GB 30 Days",
      "bundle_name": "esim_10GB_30D_IT_V2",
      "price": "32.99",
      "currency": "USD",
      "telegram_username": "maria_travel",
      "createdAt": "2024-12-24T13:45:00.000Z",
      "updatedAt": "2024-12-24T13:45:00.000Z",
      "qrCode": "https://api.qrserver.com/v1/create-qr-code/?size=300x300&data=LPA:1$rsp.airalo.com$Y1Z2-A3B4-C5D6-E7F8",
      "qr_code": "https://api.qrserver.com/v1/create-qr-code/?size=300x300&data=LPA:1$rsp.airalo.com$Y1Z2-A3B4-C5D6-E7F8"
    }
  ],
  "555666777": [
    {
      "orderReference": "ESIM-2024-12-007",
      "number": "ESIM-2024-12-007",
      "source": "telegram_mini_app",
      "customer": "555666777",
      "telegram_user_id": "555666777",
      "provider_product_id": "esim_unlimited_EU_V2",
      "provider_base_price_usd": 45.99,
      "payment_method": "telegram_stars",
      "paymentType": "telegram_stars",
      "date": "2024-12-23",
      "time": "09:15:00",
      "status": "completed",
      "iccid": "8944333344445555666",
      "matchingId": "G1H2-I3J4-K5L6-M7N8",
      "smdpAddress": "http://rsp.holafly.com",
      "rspUrl": "http://rsp.holafly.com",
      "country_code": "EU",
      "country_name": "Europe",
      "plan_id": "esim_unlimited_EU_V2",
      "plan_type": "unlimited",
      "plan_name": "Unlimited Europe 30 Days",
      "bundle_name": "esim_unlimited_EU_V2",
      "price": "49.99",
      "currency": "USD",
      "telegram_username": "john_doe",
      "createdAt": "2024-12-23T09:15:00.000Z",
      "updatedAt": "2024-12-23T09:15:00.000Z",
      "qrCode": "https://api.qrserver.com/v1/create-qr-code/?size=300x300&data=LPA:1$rsp.holafly.com$G1H2-I3J4-K5L6-M7N8",
      "qr_code": "https://api.qrserver.com/v1/create-qr-code/?size=300x300&data=LPA:1$rsp.holafly.com$G1H2-I3J4-K5L6-M7N8"
    },
    {
      "orderReference": "ESIM-2024-12-008",
      "number": "ESIM-2024-12-008",
      "source": "telegram_mini_app",
      "customer": "555666777",
      "telegram_user_id": "555666777",
      "provider_product_id": "esim_5GB_7D_JP_V2",
      "provider_base_price_usd": 22.99,
      "payment_method": "bank_card",
      "paymentType": "bank_card",
      "date": "2024-12-15",
      "time": "15:30:00",
      "status": "completed",
      "iccid": "8944777788889999000",
      "matchingId": "O1P2-Q3R4-S5T6-U7V8",
      "smdpAddress": "http://rsp.nomad.com",
      "rspUrl": "http://rsp.nomad.com",
      "country_code": "JP",
      "country_name": "Japan",
      "plan_id": "esim_5GB_7D_JP_V2",
      "plan_type": "standard",
      "plan_name": "5GB 7 Days",
      "bundle_name": "esim_5GB_7D_JP_V2",
      "price": "25.99",
      "currency": "USD",
      "telegram_username": "john_doe",
      "createdAt": "2024-12-15T15:30:00.000Z",
      "updatedAt": "2024-12-15T15:30:00.000Z",
      "qrCode": "https://api.qrserver.com/v1/create-qr-code/?size=300x300&data=LPA:1$rsp.nomad.com$O1P2-Q3R4-S5T6-U7V8",
      "qr_code": "https://api.qrserver.com/v1/create-qr-code/?size=300x300&data=LPA:1$rsp.nomad.com$O1P2-Q3R4-S5T6-U7V8"
    }
  ]
}





